{"@type":"IrProgram","classes":[{"name":"IuYj","language":"JAVA","functions":[{"name":"fwj4Uf5s","printNullableAnnotations":true,"body":{},"returnType":{"@type":"IrNullableType","innerType":{"@type":"IrBuiltInType","@name":"IrAny"}}},{"name":"wd0n","printNullableAnnotations":true,"body":{},"isFinal":true,"parameterList":[{"name":"hhx0Vh","type":{"@type":"IrPlatformType","innerType":{"@type":"IrSimpleClassifier","classDecl":"IuYj"}}},{"name":"zeM","type":{"@type":"IrPlatformType","innerType":{"@type":"IrBuiltInType","@name":"IrAny"}}}],"returnType":{"@type":"IrBuiltInType","@name":"IrAny"}}],"classKind":"OPEN"},{"name":"B0e8r0Tl","language":"KOTLIN","functions":[{"name":"jRz4Qi","body":{},"parameterList":[{"name":"zyL4ouH","type":{"@type":"IrBuiltInType","@name":"IrAny"}},{"name":"ktG","type":{"@type":"IrBuiltInType","@name":"IrAny"}}],"returnType":{"@type":"IrSimpleClassifier","classDecl":"IuYj"}},{"name":"wd0n","printNullableAnnotations":true,"body":{},"isOverride":true,"isOverrideStub":true,"override":["IuYj"],"isFinal":true,"parameterList":[{"name":"hhx0Vh","type":{"@type":"IrPlatformType","innerType":{"@type":"IrSimpleClassifier","classDecl":"IuYj"}}},{"name":"zeM","type":{"@type":"IrPlatformType","innerType":{"@type":"IrBuiltInType","@name":"IrAny"}}}],"returnType":{"@type":"IrBuiltInType","@name":"IrAny"}},{"name":"fwj4Uf5s","printNullableAnnotations":true,"body":{},"isOverride":true,"isOverrideStub":true,"override":["IuYj"],"returnType":{"@type":"IrNullableType","innerType":{"@type":"IrBuiltInType","@name":"IrAny"}}}],"classKind":"FINAL","superType":{"@type":"IrSimpleClassifier","classDecl":"IuYj"}},{"name":"Uj5v","language":"KOTLIN","functions":[{"name":"oClb","printNullableAnnotations":true,"body":{},"isFinal":true,"parameterList":[{"name":"bz1NHH","type":{"@type":"IrNullableType","innerType":{"@type":"IrSimpleClassifier","classDecl":"Uj5v"}}}],"returnType":{"@type":"IrSimpleClassifier","classDecl":"IuYj"}},{"name":"qwOMT","typeParameters":[{"@type":"IrTypeParameter","name":"T0","upperbound":{"@type":"IrSimpleClassifier","classDecl":"Uj5v"}},{"@type":"IrTypeParameter","name":"T1","upperbound":{"@type":"IrNullableType","innerType":{"@type":"IrSimpleClassifier","classDecl":"B0e8r0Tl"}}},{"@type":"IrTypeParameter","name":"T2","upperbound":{"@type":"IrNullableType","innerType":{"@type":"IrTypeParameter","name":"T1","upperbound":{"@type":"IrNullableType","innerType":{"@type":"IrSimpleClassifier","classDecl":"B0e8r0Tl"}}}}}],"parameterList":[{"name":"pG8","type":{"@type":"IrBuiltInType","@name":"IrAny"}},{"name":"nqOxrI","type":{"@type":"IrNullableType","innerType":{"@type":"IrTypeParameter","name":"T2","upperbound":{"@type":"IrNullableType","innerType":{"@type":"IrTypeParameter","name":"T1","upperbound":{"@type":"IrNullableType","innerType":{"@type":"IrSimpleClassifier","classDecl":"B0e8r0Tl"}}}}}}},{"name":"xKmt","type":{"@type":"IrNullableType","innerType":{"@type":"IrTypeParameter","name":"T0","upperbound":{"@type":"IrSimpleClassifier","classDecl":"Uj5v"}}}}],"returnType":{"@type":"IrSimpleClassifier","classDecl":"IuYj"}},{"name":"bEK7I5","body":{},"isFinal":true,"parameterList":[{"name":"tMeD","type":{"@type":"IrNullableType","innerType":{"@type":"IrSimpleClassifier","classDecl":"IuYj"}}},{"name":"tCFJcw","type":{"@type":"IrSimpleClassifier","classDecl":"Uj5v"}},{"name":"pNdI","type":{"@type":"IrSimpleClassifier","classDecl":"IuYj"}}],"returnType":{"@type":"IrNullableType","innerType":{"@type":"IrBuiltInType","@name":"IrAny"}}},{"name":"wd0n","body":{},"isOverride":true,"isOverrideStub":true,"override":["IuYj"],"isFinal":true,"parameterList":[{"name":"hhx0Vh","type":{"@type":"IrPlatformType","innerType":{"@type":"IrSimpleClassifier","classDecl":"IuYj"}}},{"name":"zeM","type":{"@type":"IrPlatformType","innerType":{"@type":"IrBuiltInType","@name":"IrAny"}}}],"returnType":{"@type":"IrBuiltInType","@name":"IrAny"}},{"name":"fwj4Uf5s","isOverride":true,"override":["IuYj"],"returnType":{"@type":"IrNullableType","innerType":{"@type":"IrBuiltInType","@name":"IrAny"}}}],"classKind":"ABSTRACT","superType":{"@type":"IrSimpleClassifier","classDecl":"IuYj"}},{"name":"MedrQo9o","language":"KOTLIN","functions":[{"name":"hJVad","body":{},"returnType":{"@type":"IrBuiltInType","@name":"IrAny"}},{"name":"fB81","body":{},"isFinal":true,"parameterList":[{"name":"wuz0kGJY","type":{"@type":"IrSimpleClassifier","classDecl":"MedrQo9o"}}],"returnType":{"@type":"IrSimpleClassifier","classDecl":"IuYj"}}],"classKind":"OPEN"},{"name":"Csw","language":"KOTLIN","functions":[{"name":"uAPbM","typeParameters":[{"@type":"IrTypeParameter","name":"T6","upperbound":{"@type":"IrNullableType","innerType":{"@type":"IrTypeParameter","name":"T4","upperbound":{"@type":"IrNullableType","innerType":{"@type":"IrBuiltInType","@name":"IrAny"}}}}},{"@type":"IrTypeParameter","name":"T7","upperbound":{"@type":"IrNullableType","innerType":{"@type":"IrTypeParameter","name":"T6","upperbound":{"@type":"IrNullableType","innerType":{"@type":"IrTypeParameter","name":"T4","upperbound":{"@type":"IrNullableType","innerType":{"@type":"IrBuiltInType","@name":"IrAny"}}}}}}}],"printNullableAnnotations":true,"body":{},"isFinal":true,"parameterList":[{"name":"ljfPC","type":{"@type":"IrNullableType","innerType":{"@type":"IrSimpleClassifier","classDecl":"IuYj"}}},{"name":"ecW1","type":{"@type":"IrPlatformType","innerType":{"@type":"IrParameterizedClassifier","classDecl":"Csw","arguments":{"T4":[{"@type":"IrTypeParameter","name":"T4","upperbound":{"@type":"IrNullableType","innerType":{"@type":"IrBuiltInType","@name":"IrAny"}}},{"@type":"IrTypeParameter","name":"T5","upperbound":{"@type":"IrSimpleClassifier","classDecl":"MedrQo9o"}}],"T5":[{"@type":"IrTypeParameter","name":"T5","upperbound":{"@type":"IrSimpleClassifier","classDecl":"MedrQo9o"}},{"@type":"IrSimpleClassifier","classDecl":"MedrQo9o"}],"T3":[{"@type":"IrTypeParameter","name":"T3","upperbound":{"@type":"IrNullableType","innerType":{"@type":"IrBuiltInType","@name":"IrAny"}}},{"@type":"IrNullableType","innerType":{"@type":"IrSimpleClassifier","classDecl":"B0e8r0Tl"}}]}}}},{"name":"bygwCuE","type":{"@type":"IrNullableType","innerType":{"@type":"IrTypeParameter","name":"T6","upperbound":{"@type":"IrNullableType","innerType":{"@type":"IrTypeParameter","name":"T4","upperbound":{"@type":"IrNullableType","innerType":{"@type":"IrBuiltInType","@name":"IrAny"}}}}}}}],"returnType":{"@type":"IrSimpleClassifier","classDecl":"IuYj"}},{"name":"wd0n","body":{},"isOverride":true,"isOverrideStub":true,"override":["IuYj"],"isFinal":true,"parameterList":[{"name":"hhx0Vh","type":{"@type":"IrPlatformType","innerType":{"@type":"IrSimpleClassifier","classDecl":"IuYj"}}},{"name":"zeM","type":{"@type":"IrPlatformType","innerType":{"@type":"IrBuiltInType","@name":"IrAny"}}}],"returnType":{"@type":"IrBuiltInType","@name":"IrAny"}},{"name":"fwj4Uf5s","printNullableAnnotations":true,"body":{},"isOverride":true,"override":["IuYj"],"isFinal":true,"returnType":{"@type":"IrNullableType","innerType":{"@type":"IrBuiltInType","@name":"IrAny"}}}],"typeParameters":[{"@type":"IrTypeParameter","name":"T3","upperbound":{"@type":"IrNullableType","innerType":{"@type":"IrBuiltInType","@name":"IrAny"}}},{"@type":"IrTypeParameter","name":"T4","upperbound":{"@type":"IrNullableType","innerType":{"@type":"IrBuiltInType","@name":"IrAny"}}},{"@type":"IrTypeParameter","name":"T5","upperbound":{"@type":"IrSimpleClassifier","classDecl":"MedrQo9o"}}],"classKind":"ABSTRACT","superType":{"@type":"IrSimpleClassifier","classDecl":"IuYj"}},{"name":"C9p","language":"JAVA","functions":[{"name":"hk0bivl","printNullableAnnotations":true,"parameterList":[{"name":"o6E","type":{"@type":"IrPlatformType","innerType":{"@type":"IrSimpleClassifier","classDecl":"B0e8r0Tl"}}},{"name":"dlrG","type":{"@type":"IrNullableType","innerType":{"@type":"IrSimpleClassifier","classDecl":"IuYj"}}},{"name":"zYDibn","type":{"@type":"IrParameterizedClassifier","classDecl":"Csw","arguments":{"T4":[{"@type":"IrTypeParameter","name":"T4","upperbound":{"@type":"IrNullableType","innerType":{"@type":"IrBuiltInType","@name":"IrAny"}}},{"@type":"IrSimpleClassifier","classDecl":"MedrQo9o"}],"T5":[{"@type":"IrTypeParameter","name":"T5","upperbound":{"@type":"IrSimpleClassifier","classDecl":"MedrQo9o"}},{"@type":"IrSimpleClassifier","classDecl":"MedrQo9o"}],"T3":[{"@type":"IrTypeParameter","name":"T3","upperbound":{"@type":"IrNullableType","innerType":{"@type":"IrBuiltInType","@name":"IrAny"}}},{"@type":"IrNullableType","innerType":{"@type":"IrSimpleClassifier","classDecl":"B0e8r0Tl"}}]}}}],"returnType":{"@type":"IrSimpleClassifier","classDecl":"B0e8r0Tl"}}],"classKind":"INTERFACE"},{"name":"BCx","language":"KOTLIN","functions":[{"name":"fTt3","body":{},"returnType":{"@type":"IrSimpleClassifier","classDecl":"MedrQo9o"}},{"name":"atH4uNJ","body":{},"isFinal":true,"parameterList":[{"name":"todsTa","type":{"@type":"IrBuiltInType","@name":"IrAny"}},{"name":"mee","type":{"@type":"IrPlatformType","innerType":{"@type":"IrTypeParameter","name":"T9","upperbound":{"@type":"IrNullableType","innerType":{"@type":"IrBuiltInType","@name":"IrAny"}}}}},{"name":"r0nj","type":{"@type":"IrSimpleClassifier","classDecl":"IuYj"}}],"returnType":{"@type":"IrSimpleClassifier","classDecl":"MedrQo9o"}},{"name":"asyxy","body":{},"isFinal":true,"parameterList":[{"name":"lBSugZ","type":{"@type":"IrNullableType","innerType":{"@type":"IrSimpleClassifier","classDecl":"Uj5v"}}},{"name":"vC7A35","type":{"@type":"IrTypeParameter","name":"T9","upperbound":{"@type":"IrNullableType","innerType":{"@type":"IrBuiltInType","@name":"IrAny"}}}},{"name":"liC","type":{"@type":"IrNullableType","innerType":{"@type":"IrTypeParameter","name":"T8","upperbound":{"@type":"IrSimpleClassifier","classDecl":"B0e8r0Tl"}}}}],"returnType":{"@type":"IrNullableType","innerType":{"@type":"IrSimpleClassifier","classDecl":"Uj5v"}}}],"typeParameters":[{"@type":"IrTypeParameter","name":"T8","upperbound":{"@type":"IrSimpleClassifier","classDecl":"B0e8r0Tl"}},{"@type":"IrTypeParameter","name":"T9","upperbound":{"@type":"IrNullableType","innerType":{"@type":"IrBuiltInType","@name":"IrAny"}}}],"classKind":"OPEN"},{"name":"Hj6r","language":"JAVA","functions":[{"name":"fuJr0oqa","parameterList":[{"name":"rJmohdg","type":{"@type":"IrPlatformType","innerType":{"@type":"IrSimpleClassifier","classDecl":"B0e8r0Tl"}}}],"returnType":{"@type":"IrNullableType","innerType":{"@type":"IrSimpleClassifier","classDecl":"Hj6r"}}},{"name":"bvXNc","printNullableAnnotations":true,"parameterList":[{"name":"ommPz","type":{"@type":"IrNullableType","innerType":{"@type":"IrSimpleClassifier","classDecl":"Hj6r"}}},{"name":"jHv0GLfW","type":{"@type":"IrSimpleClassifier","classDecl":"IuYj"}},{"name":"w2448or","type":{"@type":"IrParameterizedClassifier","classDecl":"Csw","arguments":{"T4":[{"@type":"IrTypeParameter","name":"T4","upperbound":{"@type":"IrNullableType","innerType":{"@type":"IrBuiltInType","@name":"IrAny"}}},{"@type":"IrNullableType","innerType":{"@type":"IrBuiltInType","@name":"IrAny"}}],"T5":[{"@type":"IrTypeParameter","name":"T5","upperbound":{"@type":"IrSimpleClassifier","classDecl":"MedrQo9o"}},{"@type":"IrSimpleClassifier","classDecl":"MedrQo9o"}],"T3":[{"@type":"IrTypeParameter","name":"T3","upperbound":{"@type":"IrNullableType","innerType":{"@type":"IrBuiltInType","@name":"IrAny"}}},{"@type":"IrNullableType","innerType":{"@type":"IrSimpleClassifier","classDecl":"Uj5v"}}]}}}],"returnType":{"@type":"IrNullableType","innerType":{"@type":"IrSimpleClassifier","classDecl":"B0e8r0Tl"}}},{"name":"le2","parameterList":[{"name":"l86arR","type":{"@type":"IrPlatformType","innerType":{"@type":"IrSimpleClassifier","classDecl":"MedrQo9o"}}},{"name":"q0hH","type":{"@type":"IrNullableType","innerType":{"@type":"IrSimpleClassifier","classDecl":"C9p"}}}],"returnType":{"@type":"IrParameterizedClassifier","classDecl":"BCx","arguments":{"T8":[{"@type":"IrTypeParameter","name":"T8","upperbound":{"@type":"IrSimpleClassifier","classDecl":"B0e8r0Tl"}},{"@type":"IrSimpleClassifier","classDecl":"B0e8r0Tl"}],"T9":[{"@type":"IrTypeParameter","name":"T9","upperbound":{"@type":"IrNullableType","innerType":{"@type":"IrBuiltInType","@name":"IrAny"}}},{"@type":"IrNullableType","innerType":{"@type":"IrSimpleClassifier","classDecl":"B0e8r0Tl"}}]}}},{"name":"hk0bivl","body":{},"isOverride":true,"override":["C9p"],"parameterList":[{"name":"o6E","type":{"@type":"IrPlatformType","innerType":{"@type":"IrSimpleClassifier","classDecl":"B0e8r0Tl"}}},{"name":"dlrG","type":{"@type":"IrNullableType","innerType":{"@type":"IrSimpleClassifier","classDecl":"IuYj"}}},{"name":"zYDibn","type":{"@type":"IrParameterizedClassifier","classDecl":"Csw","arguments":{"T4":[{"@type":"IrTypeParameter","name":"T4","upperbound":{"@type":"IrNullableType","innerType":{"@type":"IrBuiltInType","@name":"IrAny"}}},{"@type":"IrSimpleClassifier","classDecl":"MedrQo9o"}],"T5":[{"@type":"IrTypeParameter","name":"T5","upperbound":{"@type":"IrSimpleClassifier","classDecl":"MedrQo9o"}},{"@type":"IrSimpleClassifier","classDecl":"MedrQo9o"}],"T3":[{"@type":"IrTypeParameter","name":"T3","upperbound":{"@type":"IrNullableType","innerType":{"@type":"IrBuiltInType","@name":"IrAny"}}},{"@type":"IrNullableType","innerType":{"@type":"IrSimpleClassifier","classDecl":"B0e8r0Tl"}}]}}}],"returnType":{"@type":"IrSimpleClassifier","classDecl":"B0e8r0Tl"}}],"classKind":"INTERFACE","implementedTypes":[{"@type":"IrSimpleClassifier","classDecl":"C9p"}]},{"name":"ZPx","language":"JAVA","functions":[{"name":"mxWAp","body":{},"isFinal":true,"returnType":{"@type":"IrNullableType","innerType":{"@type":"IrSimpleClassifier","classDecl":"Hj6r"}}},{"name":"hk0bivl","printNullableAnnotations":true,"body":{},"isOverride":true,"override":["C9p"],"isFinal":true,"parameterList":[{"name":"o6E","type":{"@type":"IrPlatformType","innerType":{"@type":"IrSimpleClassifier","classDecl":"B0e8r0Tl"}}},{"name":"dlrG","type":{"@type":"IrNullableType","innerType":{"@type":"IrSimpleClassifier","classDecl":"IuYj"}}},{"name":"zYDibn","type":{"@type":"IrParameterizedClassifier","classDecl":"Csw","arguments":{"T4":[{"@type":"IrTypeParameter","name":"T4","upperbound":{"@type":"IrNullableType","innerType":{"@type":"IrBuiltInType","@name":"IrAny"}}},{"@type":"IrSimpleClassifier","classDecl":"MedrQo9o"}],"T5":[{"@type":"IrTypeParameter","name":"T5","upperbound":{"@type":"IrSimpleClassifier","classDecl":"MedrQo9o"}},{"@type":"IrSimpleClassifier","classDecl":"MedrQo9o"}],"T3":[{"@type":"IrTypeParameter","name":"T3","upperbound":{"@type":"IrNullableType","innerType":{"@type":"IrBuiltInType","@name":"IrAny"}}},{"@type":"IrNullableType","innerType":{"@type":"IrSimpleClassifier","classDecl":"B0e8r0Tl"}}]}}}],"returnType":{"@type":"IrSimpleClassifier","classDecl":"B0e8r0Tl"}},{"name":"wd0n","body":{},"isOverride":true,"isOverrideStub":true,"override":["IuYj"],"isFinal":true,"parameterList":[{"name":"hhx0Vh","type":{"@type":"IrPlatformType","innerType":{"@type":"IrSimpleClassifier","classDecl":"IuYj"}}},{"name":"zeM","type":{"@type":"IrPlatformType","innerType":{"@type":"IrBuiltInType","@name":"IrAny"}}}],"returnType":{"@type":"IrBuiltInType","@name":"IrAny"}},{"name":"fwj4Uf5s","printNullableAnnotations":true,"body":{},"isOverride":true,"override":["IuYj"],"isFinal":true,"returnType":{"@type":"IrNullableType","innerType":{"@type":"IrBuiltInType","@name":"IrAny"}}}],"classKind":"OPEN","superType":{"@type":"IrSimpleClassifier","classDecl":"IuYj"},"implementedTypes":[{"@type":"IrSimpleClassifier","classDecl":"C9p"}]},{"name":"AKh5","language":"KOTLIN","functions":[{"name":"m7btK","body":{},"returnType":{"@type":"IrBuiltInType","@name":"IrUnit"}},{"name":"a0zJqy","body":{},"isFinal":true,"returnType":{"@type":"IrNullableType","innerType":{"@type":"IrSimpleClassifier","classDecl":"IuYj"}}},{"name":"fuJr0oqa","printNullableAnnotations":true,"body":{},"isOverride":true,"override":["Hj6r"],"parameterList":[{"name":"rJmohdg","type":{"@type":"IrPlatformType","innerType":{"@type":"IrSimpleClassifier","classDecl":"B0e8r0Tl"}}}],"returnType":{"@type":"IrNullableType","innerType":{"@type":"IrSimpleClassifier","classDecl":"Hj6r"}}},{"name":"bvXNc","printNullableAnnotations":true,"body":{},"isOverride":true,"override":["Hj6r"],"parameterList":[{"name":"ommPz","type":{"@type":"IrNullableType","innerType":{"@type":"IrSimpleClassifier","classDecl":"Hj6r"}}},{"name":"jHv0GLfW","type":{"@type":"IrSimpleClassifier","classDecl":"IuYj"}},{"name":"w2448or","type":{"@type":"IrParameterizedClassifier","classDecl":"Csw","arguments":{"T4":[{"@type":"IrTypeParameter","name":"T4","upperbound":{"@type":"IrNullableType","innerType":{"@type":"IrBuiltInType","@name":"IrAny"}}},{"@type":"IrNullableType","innerType":{"@type":"IrBuiltInType","@name":"IrAny"}}],"T5":[{"@type":"IrTypeParameter","name":"T5","upperbound":{"@type":"IrSimpleClassifier","classDecl":"MedrQo9o"}},{"@type":"IrSimpleClassifier","classDecl":"MedrQo9o"}],"T3":[{"@type":"IrTypeParameter","name":"T3","upperbound":{"@type":"IrNullableType","innerType":{"@type":"IrBuiltInType","@name":"IrAny"}}},{"@type":"IrNullableType","innerType":{"@type":"IrSimpleClassifier","classDecl":"Uj5v"}}]}}}],"returnType":{"@type":"IrNullableType","innerType":{"@type":"IrSimpleClassifier","classDecl":"B0e8r0Tl"}}},{"name":"le2","printNullableAnnotations":true,"body":{},"isOverride":true,"override":["Hj6r"],"isFinal":true,"parameterList":[{"name":"l86arR","type":{"@type":"IrPlatformType","innerType":{"@type":"IrSimpleClassifier","classDecl":"MedrQo9o"}}},{"name":"q0hH","type":{"@type":"IrNullableType","innerType":{"@type":"IrSimpleClassifier","classDecl":"C9p"}}}],"returnType":{"@type":"IrParameterizedClassifier","classDecl":"BCx","arguments":{"T8":[{"@type":"IrTypeParameter","name":"T8","upperbound":{"@type":"IrSimpleClassifier","classDecl":"B0e8r0Tl"}},{"@type":"IrSimpleClassifier","classDecl":"B0e8r0Tl"}],"T9":[{"@type":"IrTypeParameter","name":"T9","upperbound":{"@type":"IrNullableType","innerType":{"@type":"IrBuiltInType","@name":"IrAny"}}},{"@type":"IrNullableType","innerType":{"@type":"IrSimpleClassifier","classDecl":"B0e8r0Tl"}}]}}},{"name":"qwOMT","typeParameters":[{"@type":"IrTypeParameter","name":"T0","upperbound":{"@type":"IrSimpleClassifier","classDecl":"Uj5v"}},{"@type":"IrTypeParameter","name":"T1","upperbound":{"@type":"IrNullableType","innerType":{"@type":"IrSimpleClassifier","classDecl":"B0e8r0Tl"}}},{"@type":"IrTypeParameter","name":"T2","upperbound":{"@type":"IrNullableType","innerType":{"@type":"IrTypeParameter","name":"T1","upperbound":{"@type":"IrNullableType","innerType":{"@type":"IrSimpleClassifier","classDecl":"B0e8r0Tl"}}}}}],"body":{},"isOverride":true,"override":["Uj5v"],"parameterList":[{"name":"pG8","type":{"@type":"IrBuiltInType","@name":"IrAny"}},{"name":"nqOxrI","type":{"@type":"IrNullableType","innerType":{"@type":"IrTypeParameter","name":"T2","upperbound":{"@type":"IrNullableType","innerType":{"@type":"IrTypeParameter","name":"T1","upperbound":{"@type":"IrNullableType","innerType":{"@type":"IrSimpleClassifier","classDecl":"B0e8r0Tl"}}}}}}},{"name":"xKmt","type":{"@type":"IrNullableType","innerType":{"@type":"IrTypeParameter","name":"T0","upperbound":{"@type":"IrSimpleClassifier","classDecl":"Uj5v"}}}}],"returnType":{"@type":"IrSimpleClassifier","classDecl":"IuYj"}},{"name":"fwj4Uf5s","printNullableAnnotations":true,"body":{},"isOverride":true,"override":["Uj5v"],"returnType":{"@type":"IrNullableType","innerType":{"@type":"IrBuiltInType","@name":"IrAny"}}},{"name":"oClb","body":{},"isOverride":true,"isOverrideStub":true,"override":["Uj5v"],"isFinal":true,"parameterList":[{"name":"bz1NHH","type":{"@type":"IrNullableType","innerType":{"@type":"IrSimpleClassifier","classDecl":"Uj5v"}}}],"returnType":{"@type":"IrSimpleClassifier","classDecl":"IuYj"}},{"name":"bEK7I5","body":{},"isOverride":true,"isOverrideStub":true,"override":["Uj5v"],"isFinal":true,"parameterList":[{"name":"tMeD","type":{"@type":"IrNullableType","innerType":{"@type":"IrSimpleClassifier","classDecl":"IuYj"}}},{"name":"tCFJcw","type":{"@type":"IrSimpleClassifier","classDecl":"Uj5v"}},{"name":"pNdI","type":{"@type":"IrSimpleClassifier","classDecl":"IuYj"}}],"returnType":{"@type":"IrNullableType","innerType":{"@type":"IrBuiltInType","@name":"IrAny"}}},{"name":"wd0n","printNullableAnnotations":true,"body":{},"isOverride":true,"isOverrideStub":true,"override":["Uj5v"],"isFinal":true,"parameterList":[{"name":"hhx0Vh","type":{"@type":"IrPlatformType","innerType":{"@type":"IrSimpleClassifier","classDecl":"IuYj"}}},{"name":"zeM","type":{"@type":"IrPlatformType","innerType":{"@type":"IrBuiltInType","@name":"IrAny"}}}],"returnType":{"@type":"IrBuiltInType","@name":"IrAny"}},{"name":"hk0bivl","body":{},"isOverride":true,"isOverrideStub":true,"override":["Hj6r"],"parameterList":[{"name":"o6E","type":{"@type":"IrPlatformType","innerType":{"@type":"IrSimpleClassifier","classDecl":"B0e8r0Tl"}}},{"name":"dlrG","type":{"@type":"IrNullableType","innerType":{"@type":"IrSimpleClassifier","classDecl":"IuYj"}}},{"name":"zYDibn","type":{"@type":"IrParameterizedClassifier","classDecl":"Csw","arguments":{"T4":[{"@type":"IrTypeParameter","name":"T4","upperbound":{"@type":"IrNullableType","innerType":{"@type":"IrBuiltInType","@name":"IrAny"}}},{"@type":"IrSimpleClassifier","classDecl":"MedrQo9o"}],"T5":[{"@type":"IrTypeParameter","name":"T5","upperbound":{"@type":"IrSimpleClassifier","classDecl":"MedrQo9o"}},{"@type":"IrSimpleClassifier","classDecl":"MedrQo9o"}],"T3":[{"@type":"IrTypeParameter","name":"T3","upperbound":{"@type":"IrNullableType","innerType":{"@type":"IrBuiltInType","@name":"IrAny"}}},{"@type":"IrNullableType","innerType":{"@type":"IrSimpleClassifier","classDecl":"B0e8r0Tl"}}]}}}],"returnType":{"@type":"IrSimpleClassifier","classDecl":"B0e8r0Tl"}}],"typeParameters":[{"@type":"IrTypeParameter","name":"T10","upperbound":{"@type":"IrSimpleClassifier","classDecl":"MedrQo9o"}}],"classKind":"FINAL","superType":{"@type":"IrSimpleClassifier","classDecl":"Uj5v"},"implementedTypes":[{"@type":"IrSimpleClassifier","classDecl":"Hj6r"}]},{"name":"EI1lI","language":"KOTLIN","functions":[{"name":"tL8cDC","printNullableAnnotations":true,"body":{},"returnType":{"@type":"IrParameterizedClassifier","classDecl":"AKh5","arguments":{"T10":[{"@type":"IrTypeParameter","name":"T10","upperbound":{"@type":"IrSimpleClassifier","classDecl":"MedrQo9o"}},{"@type":"IrSimpleClassifier","classDecl":"MedrQo9o"}]}}},{"name":"bMd0","printNullableAnnotations":true,"body":{},"returnType":{"@type":"IrParameterizedClassifier","classDecl":"EI1lI","arguments":{"T12":[{"@type":"IrTypeParameter","name":"T12","upperbound":{"@type":"IrNullableType","innerType":{"@type":"IrSimpleClassifier","classDecl":"Uj5v"}}},{"@type":"IrSimpleClassifier","classDecl":"Uj5v"}],"T11":[{"@type":"IrTypeParameter","name":"T11","upperbound":{"@type":"IrNullableType","innerType":{"@type":"IrSimpleClassifier","classDecl":"B0e8r0Tl"}}},{"@type":"IrNullableType","innerType":{"@type":"IrSimpleClassifier","classDecl":"B0e8r0Tl"}}],"T13":[{"@type":"IrTypeParameter","name":"T13","upperbound":{"@type":"IrNullableType","innerType":{"@type":"IrSimpleClassifier","classDecl":"C9p"}}},{"@type":"IrSimpleClassifier","classDecl":"Hj6r"}]}}},{"name":"hk0bivl","printNullableAnnotations":true,"body":{},"isOverride":true,"isOverrideStub":true,"override":["C9p"],"parameterList":[{"name":"o6E","type":{"@type":"IrPlatformType","innerType":{"@type":"IrSimpleClassifier","classDecl":"B0e8r0Tl"}}},{"name":"dlrG","type":{"@type":"IrNullableType","innerType":{"@type":"IrSimpleClassifier","classDecl":"IuYj"}}},{"name":"zYDibn","type":{"@type":"IrParameterizedClassifier","classDecl":"Csw","arguments":{"T4":[{"@type":"IrTypeParameter","name":"T4","upperbound":{"@type":"IrNullableType","innerType":{"@type":"IrBuiltInType","@name":"IrAny"}}},{"@type":"IrSimpleClassifier","classDecl":"MedrQo9o"}],"T5":[{"@type":"IrTypeParameter","name":"T5","upperbound":{"@type":"IrSimpleClassifier","classDecl":"MedrQo9o"}},{"@type":"IrSimpleClassifier","classDecl":"MedrQo9o"}],"T3":[{"@type":"IrTypeParameter","name":"T3","upperbound":{"@type":"IrNullableType","innerType":{"@type":"IrBuiltInType","@name":"IrAny"}}},{"@type":"IrNullableType","innerType":{"@type":"IrSimpleClassifier","classDecl":"B0e8r0Tl"}}]}}}],"returnType":{"@type":"IrSimpleClassifier","classDecl":"B0e8r0Tl"}},{"name":"uAPbM","typeParameters":[{"@type":"IrTypeParameter","name":"T6","upperbound":{"@type":"IrNullableType","innerType":{"@type":"IrTypeParameter","name":"T4","upperbound":{"@type":"IrNullableType","innerType":{"@type":"IrBuiltInType","@name":"IrAny"}}}}},{"@type":"IrTypeParameter","name":"T7","upperbound":{"@type":"IrNullableType","innerType":{"@type":"IrTypeParameter","name":"T6","upperbound":{"@type":"IrNullableType","innerType":{"@type":"IrTypeParameter","name":"T4","upperbound":{"@type":"IrNullableType","innerType":{"@type":"IrBuiltInType","@name":"IrAny"}}}}}}}],"body":{},"isOverride":true,"isOverrideStub":true,"override":["Csw"],"isFinal":true,"parameterList":[{"name":"ljfPC","type":{"@type":"IrNullableType","innerType":{"@type":"IrSimpleClassifier","classDecl":"IuYj"}}},{"name":"ecW1","type":{"@type":"IrPlatformType","innerType":{"@type":"IrParameterizedClassifier","classDecl":"Csw","arguments":{"T4":[{"@type":"IrTypeParameter","name":"T4","upperbound":{"@type":"IrNullableType","innerType":{"@type":"IrBuiltInType","@name":"IrAny"}}},{"@type":"IrTypeParameter","name":"T5","upperbound":{"@type":"IrSimpleClassifier","classDecl":"MedrQo9o"}}],"T5":[{"@type":"IrTypeParameter","name":"T5","upperbound":{"@type":"IrSimpleClassifier","classDecl":"MedrQo9o"}},{"@type":"IrSimpleClassifier","classDecl":"MedrQo9o"}],"T3":[{"@type":"IrTypeParameter","name":"T3","upperbound":{"@type":"IrNullableType","innerType":{"@type":"IrBuiltInType","@name":"IrAny"}}},{"@type":"IrNullableType","innerType":{"@type":"IrSimpleClassifier","classDecl":"B0e8r0Tl"}}]}}}},{"name":"bygwCuE","type":{"@type":"IrNullableType","innerType":{"@type":"IrTypeParameter","name":"T6","upperbound":{"@type":"IrNullableType","innerType":{"@type":"IrTypeParameter","name":"T4","upperbound":{"@type":"IrNullableType","innerType":{"@type":"IrBuiltInType","@name":"IrAny"}}}}}}}],"returnType":{"@type":"IrSimpleClassifier","classDecl":"IuYj"}},{"name":"wd0n","body":{},"isOverride":true,"isOverrideStub":true,"override":["Csw"],"isFinal":true,"parameterList":[{"name":"hhx0Vh","type":{"@type":"IrPlatformType","innerType":{"@type":"IrSimpleClassifier","classDecl":"IuYj"}}},{"name":"zeM","type":{"@type":"IrPlatformType","innerType":{"@type":"IrBuiltInType","@name":"IrAny"}}}],"returnType":{"@type":"IrBuiltInType","@name":"IrAny"}},{"name":"fwj4Uf5s","printNullableAnnotations":true,"body":{},"isOverride":true,"isOverrideStub":true,"override":["Csw"],"isFinal":true,"returnType":{"@type":"IrNullableType","innerType":{"@type":"IrBuiltInType","@name":"IrAny"}}}],"typeParameters":[{"@type":"IrTypeParameter","name":"T11","upperbound":{"@type":"IrNullableType","innerType":{"@type":"IrSimpleClassifier","classDecl":"B0e8r0Tl"}}},{"@type":"IrTypeParameter","name":"T12","upperbound":{"@type":"IrNullableType","innerType":{"@type":"IrSimpleClassifier","classDecl":"Uj5v"}}},{"@type":"IrTypeParameter","name":"T13","upperbound":{"@type":"IrNullableType","innerType":{"@type":"IrSimpleClassifier","classDecl":"C9p"}}}],"classKind":"ABSTRACT","superType":{"@type":"IrParameterizedClassifier","classDecl":"Csw","arguments":{"T4":[{"@type":"IrTypeParameter","name":"T4","upperbound":{"@type":"IrNullableType","innerType":{"@type":"IrBuiltInType","@name":"IrAny"}}},{"@type":"IrNullableType","innerType":{"@type":"IrSimpleClassifier","classDecl":"ZPx"}}],"T5":[{"@type":"IrTypeParameter","name":"T5","upperbound":{"@type":"IrSimpleClassifier","classDecl":"MedrQo9o"}},{"@type":"IrSimpleClassifier","classDecl":"MedrQo9o"}],"T3":[{"@type":"IrTypeParameter","name":"T3","upperbound":{"@type":"IrNullableType","innerType":{"@type":"IrBuiltInType","@name":"IrAny"}}},{"@type":"IrNullableType","innerType":{"@type":"IrSimpleClassifier","classDecl":"IuYj"}}]}},"allSuperTypeArguments":{"T4":[{"@type":"IrTypeParameter","name":"T4","upperbound":{"@type":"IrNullableType","innerType":{"@type":"IrBuiltInType","@name":"IrAny"}}},{"@type":"IrNullableType","innerType":{"@type":"IrSimpleClassifier","classDecl":"ZPx"}}],"T5":[{"@type":"IrTypeParameter","name":"T5","upperbound":{"@type":"IrSimpleClassifier","classDecl":"MedrQo9o"}},{"@type":"IrSimpleClassifier","classDecl":"MedrQo9o"}],"T3":[{"@type":"IrTypeParameter","name":"T3","upperbound":{"@type":"IrNullableType","innerType":{"@type":"IrBuiltInType","@name":"IrAny"}}},{"@type":"IrNullableType","innerType":{"@type":"IrSimpleClassifier","classDecl":"IuYj"}}]},"implementedTypes":[{"@type":"IrSimpleClassifier","classDecl":"C9p"}]}]}