{"@type":"IrProgram","classes":[{"name":"NT9uHmiG","language":"JAVA","functions":[{"name":"nox","printNullableAnnotations":true,"body":{},"parameterList":[{"name":"dIcBjD","type":{"@type":"IrNullableType","innerType":{"@type":"IrTypeParameter","name":"T365"}}}],"returnType":{"@type":"IrBuiltInType","@name":"IrAny"}}],"typeParameters":[{"@type":"IrTypeParameter","name":"T365"}],"classKind":"FINAL"},{"name":"LTO","language":"JAVA","functions":[{"name":"viGI","body":{},"parameterList":[{"name":"i660","type":{"@type":"IrNullableType","innerType":{"@type":"IrParameterizedClassifier","classDecl":"LTO","arguments":{"T366":[{"@type":"IrTypeParameter","name":"T366","upperbound":{"@type":"IrNullableType","innerType":{"@type":"IrBuiltInType","@name":"IrAny"}}},{"@type":"IrNullableType","innerType":{"@type":"IrBuiltInType","@name":"IrAny"}}]}}}},{"name":"oNGSkghW","type":{"@type":"IrNullableType","innerType":{"@type":"IrParameterizedClassifier","classDecl":"NT9uHmiG","arguments":{"T365":[{"@type":"IrTypeParameter","name":"T365"},{"@type":"IrBuiltInType","@name":"IrAny"}]}}}}],"returnType":{"@type":"IrNullableType","innerType":{"@type":"IrParameterizedClassifier","classDecl":"NT9uHmiG","arguments":{"T365":[{"@type":"IrTypeParameter","name":"T365"},{"@type":"IrBuiltInType","@name":"IrAny"}]}}}},{"name":"iE2yS","printNullableAnnotations":true,"body":{},"isFinal":true,"parameterList":[{"name":"nLXD","type":{"@type":"IrPlatformType","innerType":{"@type":"IrParameterizedClassifier","classDecl":"LTO","arguments":{"T366":[{"@type":"IrTypeParameter","name":"T366","upperbound":{"@type":"IrNullableType","innerType":{"@type":"IrBuiltInType","@name":"IrAny"}}},{"@type":"IrNullableType","innerType":{"@type":"IrBuiltInType","@name":"IrAny"}}]}}}},{"name":"mweBm","type":{"@type":"IrNullableType","innerType":{"@type":"IrParameterizedClassifier","classDecl":"LTO","arguments":{"T366":[{"@type":"IrTypeParameter","name":"T366","upperbound":{"@type":"IrNullableType","innerType":{"@type":"IrBuiltInType","@name":"IrAny"}}},{"@type":"IrNullableType","innerType":{"@type":"IrBuiltInType","@name":"IrAny"}}]}}}}],"returnType":{"@type":"IrNullableType","innerType":{"@type":"IrParameterizedClassifier","classDecl":"NT9uHmiG","arguments":{"T365":[{"@type":"IrTypeParameter","name":"T365"},{"@type":"IrBuiltInType","@name":"IrAny"}]}}}}],"typeParameters":[{"@type":"IrTypeParameter","name":"T366","upperbound":{"@type":"IrNullableType","innerType":{"@type":"IrBuiltInType","@name":"IrAny"}}}],"classKind":"OPEN"},{"name":"Nja","language":"JAVA","functions":[{"name":"zxg","printNullableAnnotations":true,"body":{},"isFinal":true,"parameterList":[{"name":"j2h","type":{"@type":"IrNullableType","innerType":{"@type":"IrParameterizedClassifier","classDecl":"LTO","arguments":{"T366":[{"@type":"IrTypeParameter","name":"T366","upperbound":{"@type":"IrNullableType","innerType":{"@type":"IrBuiltInType","@name":"IrAny"}}},{"@type":"IrBuiltInType","@name":"IrAny"}]}}}},{"name":"uYt","type":{"@type":"IrNullableType","innerType":{"@type":"IrBuiltInType","@name":"IrAny"}}}],"returnType":{"@type":"IrNullableType","innerType":{"@type":"IrParameterizedClassifier","classDecl":"NT9uHmiG","arguments":{"T365":[{"@type":"IrTypeParameter","name":"T365"},{"@type":"IrBuiltInType","@name":"IrAny"}]}}}}],"classKind":"OPEN"},{"name":"S1Athd","language":"JAVA","functions":[{"name":"cd8YRj","body":{},"isFinal":true,"parameterList":[{"name":"bQTBTJ","type":{"@type":"IrPlatformType","innerType":{"@type":"IrSimpleClassifier","classDecl":"Nja"}}},{"name":"jhql","type":{"@type":"IrNullableType","innerType":{"@type":"IrSimpleClassifier","classDecl":"S1Athd"}}}],"returnType":{"@type":"IrBuiltInType","@name":"IrUnit"}},{"name":"zxg","printNullableAnnotations":true,"body":{},"isOverride":true,"isOverrideStub":true,"override":["Nja"],"isFinal":true,"parameterList":[{"name":"j2h","type":{"@type":"IrNullableType","innerType":{"@type":"IrParameterizedClassifier","classDecl":"LTO","arguments":{"T366":[{"@type":"IrTypeParameter","name":"T366","upperbound":{"@type":"IrNullableType","innerType":{"@type":"IrBuiltInType","@name":"IrAny"}}},{"@type":"IrBuiltInType","@name":"IrAny"}]}}}},{"name":"uYt","type":{"@type":"IrNullableType","innerType":{"@type":"IrBuiltInType","@name":"IrAny"}}}],"returnType":{"@type":"IrNullableType","innerType":{"@type":"IrParameterizedClassifier","classDecl":"NT9uHmiG","arguments":{"T365":[{"@type":"IrTypeParameter","name":"T365"},{"@type":"IrBuiltInType","@name":"IrAny"}]}}}}],"classKind":"OPEN","superType":{"@type":"IrSimpleClassifier","classDecl":"Nja"}},{"name":"OXnY0uTk","language":"JAVA","functions":[{"name":"aGu","printNullableAnnotations":true,"returnType":{"@type":"IrParameterizedClassifier","classDecl":"LTO","arguments":{"T366":[{"@type":"IrTypeParameter","name":"T366","upperbound":{"@type":"IrNullableType","innerType":{"@type":"IrBuiltInType","@name":"IrAny"}}},{"@type":"IrNullableType","innerType":{"@type":"IrSimpleClassifier","classDecl":"OXnY0uTk"}}]}}},{"name":"kXKgec","returnType":{"@type":"IrNullableType","innerType":{"@type":"IrBuiltInType","@name":"IrAny"}}},{"name":"iE2yS","body":{},"isOverride":true,"isOverrideStub":true,"override":["LTO"],"isFinal":true,"parameterList":[{"name":"nLXD","type":{"@type":"IrPlatformType","innerType":{"@type":"IrParameterizedClassifier","classDecl":"LTO","arguments":{"T366":[{"@type":"IrTypeParameter","name":"T366","upperbound":{"@type":"IrNullableType","innerType":{"@type":"IrBuiltInType","@name":"IrAny"}}},{"@type":"IrNullableType","innerType":{"@type":"IrBuiltInType","@name":"IrAny"}}]}}}},{"name":"mweBm","type":{"@type":"IrNullableType","innerType":{"@type":"IrParameterizedClassifier","classDecl":"LTO","arguments":{"T366":[{"@type":"IrTypeParameter","name":"T366","upperbound":{"@type":"IrNullableType","innerType":{"@type":"IrBuiltInType","@name":"IrAny"}}},{"@type":"IrNullableType","innerType":{"@type":"IrBuiltInType","@name":"IrAny"}}]}}}}],"returnType":{"@type":"IrNullableType","innerType":{"@type":"IrParameterizedClassifier","classDecl":"NT9uHmiG","arguments":{"T365":[{"@type":"IrTypeParameter","name":"T365"},{"@type":"IrBuiltInType","@name":"IrAny"}]}}}},{"name":"viGI","body":{},"isOverride":true,"isOverrideStub":true,"override":["LTO"],"parameterList":[{"name":"i660","type":{"@type":"IrNullableType","innerType":{"@type":"IrParameterizedClassifier","classDecl":"LTO","arguments":{"T366":[{"@type":"IrTypeParameter","name":"T366","upperbound":{"@type":"IrNullableType","innerType":{"@type":"IrBuiltInType","@name":"IrAny"}}},{"@type":"IrNullableType","innerType":{"@type":"IrBuiltInType","@name":"IrAny"}}]}}}},{"name":"oNGSkghW","type":{"@type":"IrNullableType","innerType":{"@type":"IrParameterizedClassifier","classDecl":"NT9uHmiG","arguments":{"T365":[{"@type":"IrTypeParameter","name":"T365"},{"@type":"IrBuiltInType","@name":"IrAny"}]}}}}],"returnType":{"@type":"IrNullableType","innerType":{"@type":"IrParameterizedClassifier","classDecl":"NT9uHmiG","arguments":{"T365":[{"@type":"IrTypeParameter","name":"T365"},{"@type":"IrBuiltInType","@name":"IrAny"}]}}}}],"classKind":"ABSTRACT","superType":{"@type":"IrParameterizedClassifier","classDecl":"LTO","arguments":{"T366":[{"@type":"IrTypeParameter","name":"T366","upperbound":{"@type":"IrNullableType","innerType":{"@type":"IrBuiltInType","@name":"IrAny"}}},{"@type":"IrSimpleClassifier","classDecl":"S1Athd"}]}},"allSuperTypeArguments":{"T366":[{"@type":"IrTypeParameter","name":"T366","upperbound":{"@type":"IrNullableType","innerType":{"@type":"IrBuiltInType","@name":"IrAny"}}},{"@type":"IrSimpleClassifier","classDecl":"S1Athd"}]}},{"name":"M1u","language":"JAVA","functions":[{"name":"ulh","body":{},"isFinal":true,"parameterList":[{"name":"wHAz251","type":{"@type":"IrSimpleClassifier","classDecl":"OXnY0uTk"}},{"name":"cErN0h","type":{"@type":"IrNullableType","innerType":{"@type":"IrTypeParameter","name":"T367","upperbound":{"@type":"IrSimpleClassifier","classDecl":"Nja"}}}},{"name":"wixS0","type":{"@type":"IrNullableType","innerType":{"@type":"IrParameterizedClassifier","classDecl":"NT9uHmiG","arguments":{"T365":[{"@type":"IrTypeParameter","name":"T365"},{"@type":"IrBuiltInType","@name":"IrAny"}]}}}}],"returnType":{"@type":"IrParameterizedClassifier","classDecl":"NT9uHmiG","arguments":{"T365":[{"@type":"IrTypeParameter","name":"T365"},{"@type":"IrSimpleClassifier","classDecl":"Nja"}]}}}],"typeParameters":[{"@type":"IrTypeParameter","name":"T367","upperbound":{"@type":"IrSimpleClassifier","classDecl":"Nja"}},{"@type":"IrTypeParameter","name":"T368","upperbound":{"@type":"IrNullableType","innerType":{"@type":"IrSimpleClassifier","classDecl":"S1Athd"}}},{"@type":"IrTypeParameter","name":"T369","upperbound":{"@type":"IrTypeParameter","name":"T367","upperbound":{"@type":"IrSimpleClassifier","classDecl":"Nja"}}}],"classKind":"OPEN"},{"name":"DROH7JKl","language":"KOTLIN","functions":[{"name":"pX8aFY","typeParameters":[{"@type":"IrTypeParameter","name":"T370","upperbound":{"@type":"IrSimpleClassifier","classDecl":"DROH7JKl"}},{"@type":"IrTypeParameter","name":"T371","upperbound":{"@type":"IrNullableType","innerType":{"@type":"IrTypeParameter","name":"T370","upperbound":{"@type":"IrSimpleClassifier","classDecl":"DROH7JKl"}}}},{"@type":"IrTypeParameter","name":"T372","upperbound":{"@type":"IrNullableType","innerType":{"@type":"IrBuiltInType","@name":"IrAny"}}}],"returnType":{"@type":"IrNullableType","innerType":{"@type":"IrTypeParameter","name":"T371","upperbound":{"@type":"IrNullableType","innerType":{"@type":"IrTypeParameter","name":"T370","upperbound":{"@type":"IrSimpleClassifier","classDecl":"DROH7JKl"}}}}}},{"name":"aGu","printNullableAnnotations":true,"body":{},"isOverride":true,"override":["OXnY0uTk"],"returnType":{"@type":"IrParameterizedClassifier","classDecl":"LTO","arguments":{"T366":[{"@type":"IrTypeParameter","name":"T366","upperbound":{"@type":"IrNullableType","innerType":{"@type":"IrBuiltInType","@name":"IrAny"}}},{"@type":"IrNullableType","innerType":{"@type":"IrSimpleClassifier","classDecl":"OXnY0uTk"}}]}}},{"name":"kXKgec","printNullableAnnotations":true,"body":{},"isOverride":true,"override":["OXnY0uTk"],"returnType":{"@type":"IrNullableType","innerType":{"@type":"IrBuiltInType","@name":"IrAny"}}},{"name":"iE2yS","body":{},"isOverride":true,"isOverrideStub":true,"override":["OXnY0uTk"],"isFinal":true,"parameterList":[{"name":"nLXD","type":{"@type":"IrPlatformType","innerType":{"@type":"IrParameterizedClassifier","classDecl":"LTO","arguments":{"T366":[{"@type":"IrTypeParameter","name":"T366","upperbound":{"@type":"IrNullableType","innerType":{"@type":"IrBuiltInType","@name":"IrAny"}}},{"@type":"IrNullableType","innerType":{"@type":"IrBuiltInType","@name":"IrAny"}}]}}}},{"name":"mweBm","type":{"@type":"IrNullableType","innerType":{"@type":"IrParameterizedClassifier","classDecl":"LTO","arguments":{"T366":[{"@type":"IrTypeParameter","name":"T366","upperbound":{"@type":"IrNullableType","innerType":{"@type":"IrBuiltInType","@name":"IrAny"}}},{"@type":"IrNullableType","innerType":{"@type":"IrBuiltInType","@name":"IrAny"}}]}}}}],"returnType":{"@type":"IrNullableType","innerType":{"@type":"IrParameterizedClassifier","classDecl":"NT9uHmiG","arguments":{"T365":[{"@type":"IrTypeParameter","name":"T365"},{"@type":"IrBuiltInType","@name":"IrAny"}]}}}},{"name":"viGI","body":{},"isOverride":true,"isOverrideStub":true,"override":["OXnY0uTk"],"parameterList":[{"name":"i660","type":{"@type":"IrNullableType","innerType":{"@type":"IrParameterizedClassifier","classDecl":"LTO","arguments":{"T366":[{"@type":"IrTypeParameter","name":"T366","upperbound":{"@type":"IrNullableType","innerType":{"@type":"IrBuiltInType","@name":"IrAny"}}},{"@type":"IrNullableType","innerType":{"@type":"IrBuiltInType","@name":"IrAny"}}]}}}},{"name":"oNGSkghW","type":{"@type":"IrNullableType","innerType":{"@type":"IrParameterizedClassifier","classDecl":"NT9uHmiG","arguments":{"T365":[{"@type":"IrTypeParameter","name":"T365"},{"@type":"IrBuiltInType","@name":"IrAny"}]}}}}],"returnType":{"@type":"IrNullableType","innerType":{"@type":"IrParameterizedClassifier","classDecl":"NT9uHmiG","arguments":{"T365":[{"@type":"IrTypeParameter","name":"T365"},{"@type":"IrBuiltInType","@name":"IrAny"}]}}}}],"classKind":"ABSTRACT","superType":{"@type":"IrSimpleClassifier","classDecl":"OXnY0uTk"},"allSuperTypeArguments":{"T366":[{"@type":"IrTypeParameter","name":"T366","upperbound":{"@type":"IrNullableType","innerType":{"@type":"IrBuiltInType","@name":"IrAny"}}},{"@type":"IrSimpleClassifier","classDecl":"S1Athd"}]}},{"name":"GI1eT","language":"JAVA","functions":[{"name":"iE4rCh5","parameterList":[{"name":"kgeSdf","type":{"@type":"IrNullableType","innerType":{"@type":"IrSimpleClassifier","classDecl":"DROH7JKl"}}},{"name":"rhpj4XW2","type":{"@type":"IrPlatformType","innerType":{"@type":"IrSimpleClassifier","classDecl":"DROH7JKl"}}},{"name":"nEIQUza","type":{"@type":"IrBuiltInType","@name":"IrAny"}}],"returnType":{"@type":"IrSimpleClassifier","classDecl":"DROH7JKl"}},{"name":"mtOw6","typeParameters":[{"@type":"IrTypeParameter","name":"T375","upperbound":{"@type":"IrSimpleClassifier","classDecl":"DROH7JKl"}},{"@type":"IrTypeParameter","name":"T376","upperbound":{"@type":"IrNullableType","innerType":{"@type":"IrTypeParameter","name":"T374"}}}],"printNullableAnnotations":true,"parameterList":[{"name":"lVX6","type":{"@type":"IrNullableType","innerType":{"@type":"IrParameterizedClassifier","classDecl":"LTO","arguments":{"T366":[{"@type":"IrTypeParameter","name":"T366","upperbound":{"@type":"IrNullableType","innerType":{"@type":"IrBuiltInType","@name":"IrAny"}}},{"@type":"IrNullableType","innerType":{"@type":"IrSimpleClassifier","classDecl":"S1Athd"}}]}}}}],"returnType":{"@type":"IrNullableType","innerType":{"@type":"IrParameterizedClassifier","classDecl":"M1u","arguments":{"T369":[{"@type":"IrTypeParameter","name":"T369","upperbound":{"@type":"IrTypeParameter","name":"T367","upperbound":{"@type":"IrSimpleClassifier","classDecl":"Nja"}}},{"@type":"IrSimpleClassifier","classDecl":"Nja"}],"T367":[{"@type":"IrTypeParameter","name":"T367","upperbound":{"@type":"IrSimpleClassifier","classDecl":"Nja"}},{"@type":"IrSimpleClassifier","classDecl":"Nja"}],"T368":[{"@type":"IrTypeParameter","name":"T368","upperbound":{"@type":"IrNullableType","innerType":{"@type":"IrSimpleClassifier","classDecl":"S1Athd"}}},{"@type":"IrSimpleClassifier","classDecl":"S1Athd"}]}}}},{"name":"x2Pm","printNullableAnnotations":true,"body":{},"parameterList":[{"name":"bWt53","type":{"@type":"IrPlatformType","innerType":{"@type":"IrSimpleClassifier","classDecl":"DROH7JKl"}}},{"name":"k4n06","type":{"@type":"IrNullableType","innerType":{"@type":"IrParameterizedClassifier","classDecl":"M1u","arguments":{"T369":[{"@type":"IrTypeParameter","name":"T369","upperbound":{"@type":"IrTypeParameter","name":"T367","upperbound":{"@type":"IrSimpleClassifier","classDecl":"Nja"}}},{"@type":"IrSimpleClassifier","classDecl":"Nja"}],"T367":[{"@type":"IrTypeParameter","name":"T367","upperbound":{"@type":"IrSimpleClassifier","classDecl":"Nja"}},{"@type":"IrSimpleClassifier","classDecl":"Nja"}],"T368":[{"@type":"IrTypeParameter","name":"T368","upperbound":{"@type":"IrNullableType","innerType":{"@type":"IrSimpleClassifier","classDecl":"S1Athd"}}},{"@type":"IrSimpleClassifier","classDecl":"S1Athd"}]}}}}],"returnType":{"@type":"IrNullableType","innerType":{"@type":"IrParameterizedClassifier","classDecl":"NT9uHmiG","arguments":{"T365":[{"@type":"IrTypeParameter","name":"T365"},{"@type":"IrSimpleClassifier","classDecl":"OXnY0uTk"}]}}}},{"name":"cd8YRj","printNullableAnnotations":true,"body":{},"isOverride":true,"isOverrideStub":true,"override":["S1Athd"],"isFinal":true,"parameterList":[{"name":"bQTBTJ","type":{"@type":"IrPlatformType","innerType":{"@type":"IrSimpleClassifier","classDecl":"Nja"}}},{"name":"jhql","type":{"@type":"IrNullableType","innerType":{"@type":"IrSimpleClassifier","classDecl":"S1Athd"}}}],"returnType":{"@type":"IrBuiltInType","@name":"IrUnit"}},{"name":"zxg","printNullableAnnotations":true,"body":{},"isOverride":true,"isOverrideStub":true,"override":["S1Athd"],"isFinal":true,"parameterList":[{"name":"j2h","type":{"@type":"IrNullableType","innerType":{"@type":"IrParameterizedClassifier","classDecl":"LTO","arguments":{"T366":[{"@type":"IrTypeParameter","name":"T366","upperbound":{"@type":"IrNullableType","innerType":{"@type":"IrBuiltInType","@name":"IrAny"}}},{"@type":"IrBuiltInType","@name":"IrAny"}]}}}},{"name":"uYt","type":{"@type":"IrNullableType","innerType":{"@type":"IrBuiltInType","@name":"IrAny"}}}],"returnType":{"@type":"IrNullableType","innerType":{"@type":"IrParameterizedClassifier","classDecl":"NT9uHmiG","arguments":{"T365":[{"@type":"IrTypeParameter","name":"T365"},{"@type":"IrBuiltInType","@name":"IrAny"}]}}}}],"typeParameters":[{"@type":"IrTypeParameter","name":"T373","upperbound":{"@type":"IrSimpleClassifier","classDecl":"OXnY0uTk"}},{"@type":"IrTypeParameter","name":"T374"}],"classKind":"ABSTRACT","superType":{"@type":"IrSimpleClassifier","classDecl":"S1Athd"}},{"name":"NuYu","language":"KOTLIN","functions":[{"name":"uz6Wat","body":{},"parameterList":[{"name":"yrpDyC","type":{"@type":"IrBuiltInType","@name":"IrAny"}}],"returnType":{"@type":"IrParameterizedClassifier","classDecl":"LTO","arguments":{"T366":[{"@type":"IrTypeParameter","name":"T366","upperbound":{"@type":"IrNullableType","innerType":{"@type":"IrBuiltInType","@name":"IrAny"}}},{"@type":"IrSimpleClassifier","classDecl":"NuYu"}]}}},{"name":"ulh","printNullableAnnotations":true,"body":{},"isOverride":true,"isOverrideStub":true,"override":["M1u"],"isFinal":true,"parameterList":[{"name":"wHAz251","type":{"@type":"IrSimpleClassifier","classDecl":"OXnY0uTk"}},{"name":"cErN0h","type":{"@type":"IrNullableType","innerType":{"@type":"IrTypeParameter","name":"T367","upperbound":{"@type":"IrSimpleClassifier","classDecl":"Nja"}}}},{"name":"wixS0","type":{"@type":"IrNullableType","innerType":{"@type":"IrParameterizedClassifier","classDecl":"NT9uHmiG","arguments":{"T365":[{"@type":"IrTypeParameter","name":"T365"},{"@type":"IrBuiltInType","@name":"IrAny"}]}}}}],"returnType":{"@type":"IrParameterizedClassifier","classDecl":"NT9uHmiG","arguments":{"T365":[{"@type":"IrTypeParameter","name":"T365"},{"@type":"IrSimpleClassifier","classDecl":"Nja"}]}}}],"classKind":"ABSTRACT","superType":{"@type":"IrParameterizedClassifier","classDecl":"M1u","arguments":{"T369":[{"@type":"IrTypeParameter","name":"T369","upperbound":{"@type":"IrTypeParameter","name":"T367","upperbound":{"@type":"IrSimpleClassifier","classDecl":"Nja"}}},{"@type":"IrSimpleClassifier","classDecl":"Nja"}],"T367":[{"@type":"IrTypeParameter","name":"T367","upperbound":{"@type":"IrSimpleClassifier","classDecl":"Nja"}},{"@type":"IrSimpleClassifier","classDecl":"Nja"}],"T368":[{"@type":"IrTypeParameter","name":"T368","upperbound":{"@type":"IrNullableType","innerType":{"@type":"IrSimpleClassifier","classDecl":"S1Athd"}}},{"@type":"IrSimpleClassifier","classDecl":"S1Athd"}]}},"allSuperTypeArguments":{"T369":[{"@type":"IrTypeParameter","name":"T369","upperbound":{"@type":"IrTypeParameter","name":"T367","upperbound":{"@type":"IrSimpleClassifier","classDecl":"Nja"}}},{"@type":"IrSimpleClassifier","classDecl":"Nja"}],"T367":[{"@type":"IrTypeParameter","name":"T367","upperbound":{"@type":"IrSimpleClassifier","classDecl":"Nja"}},{"@type":"IrSimpleClassifier","classDecl":"Nja"}],"T368":[{"@type":"IrTypeParameter","name":"T368","upperbound":{"@type":"IrNullableType","innerType":{"@type":"IrSimpleClassifier","classDecl":"S1Athd"}}},{"@type":"IrSimpleClassifier","classDecl":"S1Athd"}]}},{"name":"RYKAjdpc","language":"KOTLIN","functions":[{"name":"oXhiiu","body":{},"isFinal":true,"parameterList":[{"name":"y2ztLPY","type":{"@type":"IrSimpleClassifier","classDecl":"DROH7JKl"}},{"name":"c1qw","type":{"@type":"IrNullableType","innerType":{"@type":"IrSimpleClassifier","classDecl":"Nja"}}}],"returnType":{"@type":"IrParameterizedClassifier","classDecl":"M1u","arguments":{"T369":[{"@type":"IrTypeParameter","name":"T369","upperbound":{"@type":"IrTypeParameter","name":"T367","upperbound":{"@type":"IrSimpleClassifier","classDecl":"Nja"}}},{"@type":"IrSimpleClassifier","classDecl":"Nja"}],"T367":[{"@type":"IrTypeParameter","name":"T367","upperbound":{"@type":"IrSimpleClassifier","classDecl":"Nja"}},{"@type":"IrSimpleClassifier","classDecl":"Nja"}],"T368":[{"@type":"IrTypeParameter","name":"T368","upperbound":{"@type":"IrNullableType","innerType":{"@type":"IrSimpleClassifier","classDecl":"S1Athd"}}},{"@type":"IrNullableType","innerType":{"@type":"IrSimpleClassifier","classDecl":"S1Athd"}}]}}},{"name":"vT1nKG2v","body":{},"returnType":{"@type":"IrBuiltInType","@name":"IrAny"}},{"name":"abPe597s","printNullableAnnotations":true,"body":{},"isFinal":true,"parameterList":[{"name":"f79A","type":{"@type":"IrNullableType","innerType":{"@type":"IrSimpleClassifier","classDecl":"DROH7JKl"}}}],"returnType":{"@type":"IrParameterizedClassifier","classDecl":"GI1eT","arguments":{"T374":[{"@type":"IrTypeParameter","name":"T374"},{"@type":"IrBuiltInType","@name":"IrAny"}],"T373":[{"@type":"IrTypeParameter","name":"T373","upperbound":{"@type":"IrSimpleClassifier","classDecl":"OXnY0uTk"}},{"@type":"IrSimpleClassifier","classDecl":"DROH7JKl"}]}}},{"name":"ulh","printNullableAnnotations":true,"body":{},"isOverride":true,"isOverrideStub":true,"override":["M1u"],"isFinal":true,"parameterList":[{"name":"wHAz251","type":{"@type":"IrSimpleClassifier","classDecl":"OXnY0uTk"}},{"name":"cErN0h","type":{"@type":"IrNullableType","innerType":{"@type":"IrTypeParameter","name":"T367","upperbound":{"@type":"IrSimpleClassifier","classDecl":"Nja"}}}},{"name":"wixS0","type":{"@type":"IrNullableType","innerType":{"@type":"IrParameterizedClassifier","classDecl":"NT9uHmiG","arguments":{"T365":[{"@type":"IrTypeParameter","name":"T365"},{"@type":"IrBuiltInType","@name":"IrAny"}]}}}}],"returnType":{"@type":"IrParameterizedClassifier","classDecl":"NT9uHmiG","arguments":{"T365":[{"@type":"IrTypeParameter","name":"T365"},{"@type":"IrSimpleClassifier","classDecl":"Nja"}]}}}],"classKind":"OPEN","superType":{"@type":"IrParameterizedClassifier","classDecl":"M1u","arguments":{"T369":[{"@type":"IrTypeParameter","name":"T369","upperbound":{"@type":"IrTypeParameter","name":"T367","upperbound":{"@type":"IrSimpleClassifier","classDecl":"Nja"}}},{"@type":"IrSimpleClassifier","classDecl":"Nja"}],"T367":[{"@type":"IrTypeParameter","name":"T367","upperbound":{"@type":"IrSimpleClassifier","classDecl":"Nja"}},{"@type":"IrSimpleClassifier","classDecl":"Nja"}],"T368":[{"@type":"IrTypeParameter","name":"T368","upperbound":{"@type":"IrNullableType","innerType":{"@type":"IrSimpleClassifier","classDecl":"S1Athd"}}},{"@type":"IrNullableType","innerType":{"@type":"IrSimpleClassifier","classDecl":"S1Athd"}}]}},"allSuperTypeArguments":{"T369":[{"@type":"IrTypeParameter","name":"T369","upperbound":{"@type":"IrTypeParameter","name":"T367","upperbound":{"@type":"IrSimpleClassifier","classDecl":"Nja"}}},{"@type":"IrSimpleClassifier","classDecl":"Nja"}],"T367":[{"@type":"IrTypeParameter","name":"T367","upperbound":{"@type":"IrSimpleClassifier","classDecl":"Nja"}},{"@type":"IrSimpleClassifier","classDecl":"Nja"}],"T368":[{"@type":"IrTypeParameter","name":"T368","upperbound":{"@type":"IrNullableType","innerType":{"@type":"IrSimpleClassifier","classDecl":"S1Athd"}}},{"@type":"IrNullableType","innerType":{"@type":"IrSimpleClassifier","classDecl":"S1Athd"}}]}}]}